purview/__init__.py
purview-0.0.1.dist-info/licenses/LICENSE
purview-0.0.1.dist-info/METADATA
purview-0.0.1.dist-info/WHEEL
purview-0.0.1.dist-info/top_level.txt
purview-0.0.1.dist-info/RECORD
