Metadata-Version: 2.4
Name: purview
Version: 0.0.1
Summary: A Python library for exploratory data analysis
Author-email: LattIQ Development Team <dev@lattiq.com>
License: MIT
Project-URL: Homepage, https://github.com/lattiq/purview
Project-URL: Repository, https://github.com/lattiq/purview
Keywords: data analysis,exploratory data analysis,eda
Classifier: Development Status :: 2 - Pre-Alpha
Classifier: Intended Audience :: Developers
Classifier: License :: OSI Approved :: MIT License
Classifier: Operating System :: OS Independent
Classifier: Programming Language :: Python :: 3
Classifier: Programming Language :: Python :: 3.8
Classifier: Programming Language :: Python :: 3.9
Classifier: Programming Language :: Python :: 3.10
Classifier: Programming Language :: Python :: 3.11
Classifier: Programming Language :: Python :: 3.12
Classifier: Topic :: Scientific/Engineering
Classifier: Topic :: Software Development :: Libraries :: Python Modules
Requires-Python: >=3.8
License-File: LICENSE
Dynamic: license-file
